[
  {
    "semester": "Semester 1",
    "modules": [
      {
        "name": "Algèbre Linéaire",
        "file": "https://drive.google.com/file/d/1b0ZdeGgQaYqLH1n135MopKrTyy5VYLEP/view?usp=drive_link",
        "description": "Learn about vector spaces, matrices, and linear transformations."
      },
      {
        "name": "Réseaux",
        "file": "https://drive.google.com/file/d/19wOQqqL191LP3ekKA9ki7ZFC4uH2mPD9/view?usp=drive_link",
        "description": "Understand the fundamentals of computer networks and protocols."
      },
      {
        "name": "Bases de Données",
        "file": "https://drive.google.com/file/d/1l0UY7SXWp1X0bTQrGNbuDRT0_1t4EZUB/view?usp=drive_link",
        "description": "Master database design, SQL, and data management."
      },
      {
        "name": "SE Linux",
        "file": "https://drive.google.com/file/d/162U7JtwbviTpx1INJOonQLyEugSuSVmM/view?usp=drive_link",
        "description": "Learn about SELinux for system security and access control."
      },
      {
        "name": "POO",
        "file": "https://drive.google.com/file/d/1vNfTKQYXnAEz3sAtAStqqLWtt9P8GWQM/view?usp=drive_link",
        "description": "Dive into object-oriented programming principles with C++."
      }
    ]
  },
  {
    "semester": "Semester 2",
    "modules": [
      {
        "name": "coming soon",
        "file": "#",
        "description": "coming soon."
      }
    ]
  }
]
